.gitignore
.travis.yml
CHANGES.rst
CONTRIBUTORS.rst
MANIFEST.in
README.rst
base.cfg
bootstrap.py
buildout.cfg
plone-4.3.x.cfg
plone-5.2.x.cfg
requirements-4.3.x.txt
requirements.txt
setup.py
travis.cfg
docs/LICENSE.GPL
docs/LICENSE.txt
src/collective/__init__.py
src/collective.anysurfer.egg-info/PKG-INFO
src/collective.anysurfer.egg-info/SOURCES.txt
src/collective.anysurfer.egg-info/dependency_links.txt
src/collective.anysurfer.egg-info/entry_points.txt
src/collective.anysurfer.egg-info/namespace_packages.txt
src/collective.anysurfer.egg-info/not-zip-safe
src/collective.anysurfer.egg-info/requires.txt
src/collective.anysurfer.egg-info/top_level.txt
src/collective/anysurfer/__init__.py
src/collective/anysurfer/configure.zcml
src/collective/anysurfer/context.py
src/collective/anysurfer/interfaces.py
src/collective/anysurfer/layout.py
src/collective/anysurfer/permissions.zcml
src/collective/anysurfer/setuphandlers.py
src/collective/anysurfer/testing.py
src/collective/anysurfer/transform.py
src/collective/anysurfer/upgrades.py
src/collective/anysurfer/upgrades.zcml
src/collective/anysurfer/utils.py
src/collective/anysurfer/viewlets.py
src/collective/anysurfer/browser/__init__.py
src/collective/anysurfer/browser/configure.zcml
src/collective/anysurfer/browser/controlpanel.py
src/collective/anysurfer/browser/default_accessibility_text.pt
src/collective/anysurfer/browser/plone5_path_bar.pt
src/collective/anysurfer/browser/search_plone4.js
src/collective/anysurfer/browser/search_plone5.js
src/collective/anysurfer/browser/views.py
src/collective/anysurfer/browser/overrides/Products.CMFPlone.browser.templates.accessibility-info.pt
src/collective/anysurfer/browser/overrides/Products.CMFPlone.browser.templates.search.pt
src/collective/anysurfer/browser/overrides/Products.CMFPlone.skins.plone_templates.accessibility-info.pt
src/collective/anysurfer/browser/overrides/plone.app.search.search.pt
src/collective/anysurfer/browser/static/anysurfer.png
src/collective/anysurfer/locales/collective.anysurfer.pot
src/collective/anysurfer/locales/update.sh
src/collective/anysurfer/locales/en/LC_MESSAGES/collective.anysurfer.po
src/collective/anysurfer/locales/en/LC_MESSAGES/plone.po
src/collective/anysurfer/locales/fr/LC_MESSAGES/collective.anysurfer.po
src/collective/anysurfer/locales/fr/LC_MESSAGES/plone.po
