Metadata-Version: 2.1
Name: collective.anysurfer
Version: 1.4.7
Summary: Anysurfer (Belgian accessibility standard) support for Plone
Home-page: https://github.com/collective/collective.anysurfer/
Author: 
Author-email: 
License: gpl
Platform: UNKNOWN
Classifier: Environment :: Web Environment
Classifier: Framework :: Plone
Classifier: Framework :: Plone :: 4.3
Classifier: Framework :: Plone :: 5.2
Classifier: Framework :: Plone :: 6.0
Classifier: Programming Language :: Python
Classifier: Programming Language :: Python :: 2.7
Classifier: Programming Language :: Python :: 3.7
Classifier: Operating System :: OS Independent
Classifier: License :: OSI Approved :: GNU General Public License v2 (GPLv2)
Provides-Extra: test
